[{"hour":0,"trips":13},{"hour":1,"trips":14},{"hour":2,"trips":7},{"hour":3,"trips":5},{"hour":4,"trips":1},{"hour":5,"trips":1},{"hour":6,"trips":70},{"hour":7,"trips":105},{"hour":8,"trips":91},{"hour":9,"trips":45},{"hour":10,"trips":41},{"hour":11,"trips":64},{"hour":12,"trips":57},{"hour":13,"trips":86},{"hour":14,"trips":55},{"hour":15,"trips":69},{"hour":16,"trips":81},{"hour":17,"trips":86},{"hour":18,"trips":75},{"hour":19,"trips":37},{"hour":20,"trips":28},{"hour":21,"trips":17},{"hour":22,"trips":22},{"hour":23,"trips":11}]