[{"hour":0,"trips":58},{"hour":1,"trips":31},{"hour":2,"trips":17},{"hour":3,"trips":14},{"hour":4,"trips":7},{"hour":5,"trips":94},{"hour":6,"trips":87},{"hour":7,"trips":312},{"hour":8,"trips":375},{"hour":9,"trips":341},{"hour":10,"trips":380},{"hour":11,"trips":468},{"hour":12,"trips":523},{"hour":13,"trips":600},{"hour":14,"trips":624},{"hour":15,"trips":665},{"hour":16,"trips":1065},{"hour":17,"trips":1491},{"hour":18,"trips":999},{"hour":19,"trips":660},{"hour":20,"trips":422},{"hour":21,"trips":272},{"hour":22,"trips":224},{"hour":23,"trips":112}]