[{"hour":0,"trips":21},{"hour":1,"trips":16},{"hour":2,"trips":7},{"hour":3,"trips":7},{"hour":4,"trips":9},{"hour":5,"trips":20},{"hour":6,"trips":56},{"hour":7,"trips":82},{"hour":8,"trips":91},{"hour":9,"trips":42},{"hour":10,"trips":49},{"hour":11,"trips":53},{"hour":12,"trips":82},{"hour":13,"trips":90},{"hour":14,"trips":67},{"hour":15,"trips":76},{"hour":16,"trips":115},{"hour":17,"trips":132},{"hour":18,"trips":178},{"hour":19,"trips":76},{"hour":20,"trips":71},{"hour":21,"trips":37},{"hour":22,"trips":56},{"hour":23,"trips":46}]