[{"hour":0,"trips":26},{"hour":1,"trips":17},{"hour":2,"trips":13},{"hour":3,"trips":7},{"hour":4,"trips":3},{"hour":5,"trips":10},{"hour":6,"trips":66},{"hour":7,"trips":152},{"hour":8,"trips":151},{"hour":9,"trips":62},{"hour":10,"trips":73},{"hour":11,"trips":88},{"hour":12,"trips":77},{"hour":13,"trips":103},{"hour":14,"trips":75},{"hour":15,"trips":101},{"hour":16,"trips":252},{"hour":17,"trips":420},{"hour":18,"trips":344},{"hour":19,"trips":240},{"hour":20,"trips":158},{"hour":21,"trips":88},{"hour":22,"trips":62},{"hour":23,"trips":39}]