[{"hour":0,"trips":10},{"hour":1,"trips":3},{"hour":2,"trips":3},{"hour":3,"trips":1},{"hour":4,"trips":11},{"hour":5,"trips":302},{"hour":6,"trips":1163},{"hour":7,"trips":2725},{"hour":8,"trips":3710},{"hour":9,"trips":993},{"hour":10,"trips":409},{"hour":11,"trips":479},{"hour":12,"trips":710},{"hour":13,"trips":631},{"hour":14,"trips":416},{"hour":15,"trips":482},{"hour":16,"trips":1080},{"hour":17,"trips":876},{"hour":18,"trips":304},{"hour":19,"trips":138},{"hour":20,"trips":113},{"hour":21,"trips":65},{"hour":22,"trips":50},{"hour":23,"trips":26}]